markupsafe-stubs/METADATA.toml
markupsafe-stubs/__init__.pyi
markupsafe-stubs/_compat.pyi
markupsafe-stubs/_constants.pyi
markupsafe-stubs/_native.pyi
markupsafe-stubs/_speedups.pyi
types_MarkupSafe-1.1.9.dist-info/METADATA
types_MarkupSafe-1.1.9.dist-info/WHEEL
types_MarkupSafe-1.1.9.dist-info/top_level.txt
types_MarkupSafe-1.1.9.dist-info/RECORD
